{"rank": 80, "name": "Good Will Hunting", "year": "1997", "rating": 8.3, "topic": [["film", "The", "life", "Sean", "one", "I", "genius", "Lambeau", "characters", "movie"], ["movie", "The", "I", "Sean", "film", "Damon", "It", "life", "one", "like"], ["Sean", "The", "Lambeau", "Erdos", "film", "Damon", "genius", "one", "story", "Maguire"], ["I", "movie", "Damon", "film", "The", "one", "Matt", "Williams", "Robin", "Affleck"], ["movie", "I", "The", "Damon", "genius", "Williams", "Matt", "life", "film", "Robin"], ["love", "Affleck", "story", "damon", "world", "He", "affleck", "perfect", "A", "real"], ["film", "I", "The", "Damon", "Williams", "Robin", "Matt", "Affleck", "movie", "Ben"], ["I", "movie", "Williams", "Robin", "see", "film", "like", "The", "Damon", "would"], ["I", "film", "movie", "like", "The", "character", "story", "one", "script", "This"], ["I", "like", "movie", "Williams", "know", "Robin", "film", "life", "Damon", "Sean"]]}