{"rank": 165, "name": "The Secret in Their Eyes", "year": "2009", "rating": 8.1, "topic": [["I", "movie", "It", "film", "story", "This", "life", "love", "one", "time"], ["film", "detective", "crime", "movie", "El", "secreto", "law", "ojos", "sus", "case"], ["Esposito", "Morales", "past", "life", "story", "novel", "film", "writing", "well", "rather"], ["film", "case", "Benjamin", "Irene", "Esposito", "movie", "murder", "It", "love", "one"], ["I", "film", "Ricardo", "love", "case", "one", "story", "Esposito", "years", "Benjam\u00edn"], ["film", "one", "love", "story", "I", "This", "characters", "It", "good", "makes"], ["I", "movie", "male", "Sandoval", "great", "scene", "acting", "like", "You", "female"], ["movie", "I", "story", "one", "like", "film", "This", "love", "made", "It"], ["I", "movie", "film", "one", "story", "It", "good", "love", "This", "great"], ["Esposito", "movie", "life", "characters", "love", "years", "thriller", "crime", "A", "murder"]]}